brasciichart.py
brasciichart-0.2.0.dist-info/licenses/LICENSE
brasciichart-0.2.0.dist-info/METADATA
brasciichart-0.2.0.dist-info/WHEEL
brasciichart-0.2.0.dist-info/entry_points.txt
brasciichart-0.2.0.dist-info/top_level.txt
brasciichart-0.2.0.dist-info/RECORD
