Metadata-Version: 2.4
Name: brasciichart
Version: 0.2.0
Summary: Console ASCII line charts with Braille characters
Author: Cthulhu Fhtagn
License: MIT
Project-URL: Homepage, https://codeberg.org/cthulhu/brasciichart
Project-URL: Issues, https://codeberg.org/cthulhu/brasciichart/issues
Classifier: Programming Language :: Python :: 3
Classifier: Operating System :: OS Independent
Requires-Python: >=3.7
License-File: LICENSE
Dynamic: license-file
